napkin/__init__.py
napkin/__main__.py
napkin/cli.py
napkin/gen_plantuml.py
napkin/gen_plantuml_img.py
napkin/gen_plantuml_png.py
napkin/gen_plantuml_svg.py
napkin/gen_plantuml_txt.py
napkin/plantuml_cli.py
napkin/sd.py
napkin/sd_action.py
napkin/util.py
tests/__init__.py
tests/test_decorator.py
tests/test_sd.py
tests/test_sd_frag.py
tests/test_util.py
napkin-0.6.9.dist-info/LICENSE
napkin-0.6.9.dist-info/METADATA
napkin-0.6.9.dist-info/WHEEL
napkin-0.6.9.dist-info/entry_points.txt
napkin-0.6.9.dist-info/top_level.txt
napkin-0.6.9.dist-info/RECORD
