Metadata-Version: 2.1
Name: napkin
Version: 0.6.9
Summary: Python DSL for writing PlantUML sequence diagram
Home-page: https://github.com/pinetr2e/napkin
Author: Hans Jang
Author-email: hsjang8848@gmail.com
License: UNKNOWN
Platform: UNKNOWN
Classifier: Development Status :: 3 - Alpha
Classifier: Programming Language :: Python :: 3
Classifier: Programming Language :: Python :: 3.4
Classifier: Programming Language :: Python :: 3.5
Classifier: Programming Language :: Python :: 3.6
Classifier: Programming Language :: Python :: 3.7
Classifier: Programming Language :: Python :: 3.8
Classifier: License :: OSI Approved :: MIT License
Classifier: Operating System :: OS Independent
Classifier: Intended Audience :: Developers
Classifier: Environment :: Console
Classifier: Topic :: Software Development
License-File: LICENSE
Requires-Dist: requests
